LICENSE
MANIFEST.in
README.rst
setup.py
analytics/__init__.py
analytics/utils.py
analytics.egg-info/PKG-INFO
analytics.egg-info/SOURCES.txt
analytics.egg-info/dependency_links.txt
analytics.egg-info/requires.txt
analytics.egg-info/top_level.txt
analytics/backends/__init__.py
analytics/backends/base.py
analytics/backends/dummy.py
analytics/backends/redis.py
tests/analytics/__init__.py
tests/analytics/backends/__init__.py
tests/analytics/backends/redis_test.py