Metadata-Version: 1.0
Name: analytics
Version: 0.6.5
Summary: Library for efficiently adding analytics to your project.
Home-page: https://github.com/numan/py-analytics
Author: Numan Sachwani
Author-email: numan856@gmail.com
License: Apache License 2.0
Platform: UNKNOWN
Classifier: Intended Audience :: Developers
Classifier: Intended Audience :: System Administrators
Classifier: Programming Language :: Python
Classifier: Topic :: Software Development
Classifier: Topic :: Utilities
